{
  "version": "1.0.0",
  "generated_at": "2026-02-03T14:00:00Z",
  "description": "RPC READ_SAFE - Autorisees pour tous les roles",
  "total": 154,
  "functions": [
    {"name": "calc_article_bf", "volatility": "IMMUTABLE", "reason": "Pure calculation"},
    {"name": "calc_brand_bf", "volatility": "IMMUTABLE", "reason": "Pure calculation"},
    {"name": "calc_business_fingerprint", "volatility": "IMMUTABLE", "reason": "Pure calculation"},
    {"name": "calc_vehicle_bf", "volatility": "IMMUTABLE", "reason": "Pure calculation"},
    {"name": "calculate_product_score", "volatility": "IMMUTABLE", "reason": "Pure calculation"},
    {"name": "calculate_quality_score", "volatility": "VOLATILE", "reason": "SELECT only"},
    {"name": "calculate_seo_score_gate", "volatility": "VOLATILE", "reason": "SELECT only"},
    {"name": "calculate_text_similarity", "volatility": "VOLATILE", "reason": "SELECT only"},
    {"name": "check_all_content_lengths", "volatility": "VOLATILE", "reason": "Validation only"},
    {"name": "check_all_object_associations", "volatility": "VOLATILE", "reason": "Validation only"},
    {"name": "check_ambiguous_terms", "volatility": "VOLATILE", "reason": "Validation only"},
    {"name": "check_claims_tiered", "volatility": "VOLATILE", "reason": "Validation only"},
    {"name": "check_compatibility_proof", "volatility": "VOLATILE", "reason": "Validation only"},
    {"name": "check_completeness", "volatility": "VOLATILE", "reason": "Validation only"},
    {"name": "check_confusion_pairs", "volatility": "VOLATILE", "reason": "Validation only"},
    {"name": "check_content_length", "volatility": "VOLATILE", "reason": "Validation only"},
    {"name": "check_cooccurrence", "volatility": "VOLATILE", "reason": "Validation only"},
    {"name": "check_database_health", "volatility": "VOLATILE", "reason": "Monitoring only"},
    {"name": "check_duplicate_content", "volatility": "VOLATILE", "reason": "Validation only"},
    {"name": "check_freinage_rules", "volatility": "VOLATILE", "reason": "Validation only"},
    {"name": "check_heading_structure", "volatility": "VOLATILE", "reason": "Validation only"},
    {"name": "check_internal_contradictions", "volatility": "VOLATILE", "reason": "Validation only"},
    {"name": "check_lexique_confusion", "volatility": "VOLATILE", "reason": "Validation only"},
    {"name": "check_lexique_cross_component", "volatility": "VOLATILE", "reason": "Validation only"},
    {"name": "check_object_associations", "volatility": "VOLATILE", "reason": "Validation only"},
    {"name": "check_product_completeness", "volatility": "VOLATILE", "reason": "Validation only"},
    {"name": "check_product_completeness_v2", "volatility": "STABLE", "reason": "Validation only"},
    {"name": "check_rm_products_integrity", "volatility": "VOLATILE", "reason": "Validation only"},
    {"name": "check_subsystem_integrity", "volatility": "VOLATILE", "reason": "Validation only"},
    {"name": "check_threshold", "volatility": "STABLE", "reason": "Validation only"},
    {"name": "check_unresolved_variables", "volatility": "VOLATILE", "reason": "Validation only"},
    {"name": "check_variable_hallucination", "volatility": "VOLATILE", "reason": "Validation only"},
    {"name": "check_vehicle_compatibility_claim", "volatility": "VOLATILE", "reason": "Validation only"},
    {"name": "check_vehicle_compatibility_full", "volatility": "VOLATILE", "reason": "Validation only"},
    {"name": "compute_seo_indexable", "volatility": "STABLE", "reason": "Pure calculation"},
    {"name": "count_sitemap_urls_by_temperature", "volatility": "VOLATILE", "reason": "SELECT only"},
    {"name": "count_words", "volatility": "IMMUTABLE", "reason": "Pure calculation"},
    {"name": "decode_html_entities", "volatility": "IMMUTABLE", "reason": "Pure transformation"},
    {"name": "detect_components_in_text", "volatility": "VOLATILE", "reason": "SELECT only"},
    {"name": "determine_indexation_status", "volatility": "VOLATILE", "reason": "Pure calculation"},
    {"name": "determine_product_quality", "volatility": "IMMUTABLE", "reason": "Pure calculation"},
    {"name": "determine_stock_status", "volatility": "IMMUTABLE", "reason": "Pure calculation"},
    {"name": "evaluate_business_rules", "volatility": "VOLATILE", "reason": "SELECT only"},
    {"name": "evaluate_rule_condition", "volatility": "VOLATILE", "reason": "SELECT only"},
    {"name": "fix_utf8_encoding", "volatility": "VOLATILE", "reason": "Pure transformation"},
    {"name": "get_action_definition", "volatility": "STABLE", "reason": "SELECT only"},
    {"name": "get_all_seo_observables_for_sitemap", "volatility": "STABLE", "reason": "SELECT only"},
    {"name": "get_auto_types_batch", "volatility": "STABLE", "reason": "SELECT only"},
    {"name": "get_automecanik_id", "volatility": "STABLE", "reason": "SELECT only"},
    {"name": "get_brands_with_pieces", "volatility": "STABLE", "reason": "SELECT only"},
    {"name": "get_cart_stats", "volatility": "VOLATILE", "reason": "SELECT only"},
    {"name": "get_catalog_families_for_vehicle", "volatility": "VOLATILE", "reason": "SELECT only"},
    {"name": "get_catalog_families_for_vehicle_optimized", "volatility": "VOLATILE", "reason": "SELECT only"},
    {"name": "get_catalog_hierarchy_optimized", "volatility": "VOLATILE", "reason": "SELECT only"},
    {"name": "get_catalog_legacy", "volatility": "VOLATILE", "reason": "SELECT only"},
    {"name": "get_catalog_mapping_stats", "volatility": "STABLE", "reason": "SELECT only"},
    {"name": "get_catalog_type_ids_for_gamme", "volatility": "VOLATILE", "reason": "SELECT only"},
    {"name": "get_external_id", "volatility": "STABLE", "reason": "SELECT only"},
    {"name": "get_extras_v4_type_ids", "volatility": "VOLATILE", "reason": "SELECT only"},
    {"name": "get_facet_config", "volatility": "STABLE", "reason": "SELECT only"},
    {"name": "get_family_completeness_stats", "volatility": "VOLATILE", "reason": "SELECT only"},
    {"name": "get_gamme_data_v3", "volatility": "STABLE", "reason": "SELECT only"},
    {"name": "get_gamme_page_data", "volatility": "VOLATILE", "reason": "SELECT only"},
    {"name": "get_gammes_for_family_and_vehicle", "volatility": "VOLATILE", "reason": "SELECT only"},
    {"name": "get_gammes_with_pieces", "volatility": "STABLE", "reason": "SELECT only"},
    {"name": "get_listing_products_extended", "volatility": "STABLE", "reason": "SELECT only"},
    {"name": "get_listing_products_for_build_v2", "volatility": "STABLE", "reason": "SELECT only"},
    {"name": "get_mandatory_fields", "volatility": "STABLE", "reason": "SELECT only"},
    {"name": "get_missing_v4_type_ids", "volatility": "VOLATILE", "reason": "SELECT only"},
    {"name": "get_penalty", "volatility": "STABLE", "reason": "SELECT only"},
    {"name": "get_seo_critical_alerts", "volatility": "VOLATILE", "reason": "SELECT only"},
    {"name": "get_seo_observable_by_slug", "volatility": "VOLATILE", "reason": "SELECT only"},
    {"name": "get_seo_observables_by_cluster", "volatility": "STABLE", "reason": "SELECT only"},
    {"name": "get_seo_quality_daily_stats", "volatility": "VOLATILE", "reason": "SELECT only"},
    {"name": "get_seo_reference_by_slug", "volatility": "VOLATILE", "reason": "SELECT only"},
    {"name": "get_sitemap_urls_by_temperature", "volatility": "VOLATILE", "reason": "SELECT only"},
    {"name": "get_stabilize_pages", "volatility": "VOLATILE", "reason": "SELECT only"},
    {"name": "get_staging_stats", "volatility": "STABLE", "reason": "SELECT only"},
    {"name": "get_subsystem_components", "volatility": "STABLE", "reason": "SELECT only"},
    {"name": "get_threshold", "volatility": "STABLE", "reason": "SELECT only"},
    {"name": "get_top_money_gammes", "volatility": "VOLATILE", "reason": "SELECT only"},
    {"name": "get_vehicle_compatible_gammes_php", "volatility": "STABLE", "reason": "SELECT only"},
    {"name": "get_vlevel_champions", "volatility": "VOLATILE", "reason": "SELECT only"},
    {"name": "get_vlevel_dashboard", "volatility": "STABLE", "reason": "SELECT only"},
    {"name": "get_vlevel_data", "volatility": "VOLATILE", "reason": "SELECT only"},
    {"name": "get_vlevel_section_k_extras", "volatility": "VOLATILE", "reason": "SELECT only"},
    {"name": "get_vlevel_section_k_metrics", "volatility": "VOLATILE", "reason": "SELECT only"},
    {"name": "get_vlevel_section_k_missing", "volatility": "VOLATILE", "reason": "SELECT only"},
    {"name": "get_zone_severity", "volatility": "STABLE", "reason": "SELECT only"},
    {"name": "is_import_running", "volatility": "STABLE", "reason": "SELECT only"},
    {"name": "jsonb_object_keys_count", "volatility": "IMMUTABLE", "reason": "Pure calculation"},
    {"name": "kg_calculate_adapted_interval", "volatility": "STABLE", "reason": "SELECT only"},
    {"name": "kg_calculate_bayesian_weight", "volatility": "VOLATILE", "reason": "SELECT only"},
    {"name": "kg_calculate_confidence_score", "volatility": "STABLE", "reason": "SELECT only"},
    {"name": "kg_calculate_risk_level", "volatility": "STABLE", "reason": "SELECT only"},
    {"name": "kg_calculate_truth_label_reliability", "volatility": "STABLE", "reason": "SELECT only"},
    {"name": "kg_calculate_weight_with_truth_labels", "volatility": "VOLATILE", "reason": "SELECT only"},
    {"name": "kg_check_safety_gate", "volatility": "STABLE", "reason": "SELECT only"},
    {"name": "kg_diagnose_by_labels", "volatility": "STABLE", "reason": "SELECT only"},
    {"name": "kg_diagnose_contextual", "volatility": "STABLE", "reason": "SELECT only"},
    {"name": "kg_diagnose_vehicle_aware", "volatility": "STABLE", "reason": "SELECT only"},
    {"name": "kg_diagnose_with_explainable_score", "volatility": "STABLE", "reason": "SELECT only"},
    {"name": "kg_diagnose_with_safety", "volatility": "STABLE", "reason": "SELECT only"},
    {"name": "kg_explain_diagnosis_result", "volatility": "STABLE", "reason": "SELECT only"},
    {"name": "kg_find_actions_for_fault", "volatility": "STABLE", "reason": "SELECT only"},
    {"name": "kg_find_faults_from_observables", "volatility": "STABLE", "reason": "SELECT only"},
    {"name": "kg_find_parts_for_fault", "volatility": "STABLE", "reason": "SELECT only"},
    {"name": "kg_generate_batch_explanations", "volatility": "STABLE", "reason": "SELECT only"},
    {"name": "kg_generate_explainable_diagnostic", "volatility": "STABLE", "reason": "SELECT only"},
    {"name": "kg_get_edge_type_weight_multiplier", "volatility": "IMMUTABLE", "reason": "Pure calculation"},
    {"name": "kg_get_input_type_confidence", "volatility": "IMMUTABLE", "reason": "Pure calculation"},
    {"name": "kg_get_learning_stats", "volatility": "STABLE", "reason": "SELECT only"},
    {"name": "kg_get_vehicle_maintenance_schedule", "volatility": "STABLE", "reason": "SELECT only"},
    {"name": "kg_get_vehicle_recalls", "volatility": "STABLE", "reason": "SELECT only"},
    {"name": "kg_quality_report", "volatility": "STABLE", "reason": "SELECT only"},
    {"name": "kg_rag_file_needs_sync", "volatility": "STABLE", "reason": "SELECT only"},
    {"name": "kg_rag_get_node_id", "volatility": "STABLE", "reason": "SELECT only"},
    {"name": "map_facets_to_filter_keys", "volatility": "IMMUTABLE", "reason": "Pure calculation"},
    {"name": "match_keyword_to_type", "volatility": "VOLATILE", "reason": "SELECT only"},
    {"name": "match_keywords_batch", "volatility": "VOLATILE", "reason": "SELECT only"},
    {"name": "match_keywords_batch_clean", "volatility": "VOLATILE", "reason": "SELECT only"},
    {"name": "normalize_brand_name", "volatility": "IMMUTABLE", "reason": "Pure transformation"},
    {"name": "process_prix_pas_cher", "volatility": "IMMUTABLE", "reason": "Pure transformation"},
    {"name": "process_seo_switch", "volatility": "IMMUTABLE", "reason": "Pure transformation"},
    {"name": "process_seo_template", "volatility": "STABLE", "reason": "Pure transformation"},
    {"name": "search_pieces_fts", "volatility": "STABLE", "reason": "SELECT only"},
    {"name": "search_pieces_hybrid", "volatility": "STABLE", "reason": "SELECT only"},
    {"name": "search_rag_knowledge", "volatility": "VOLATILE", "reason": "SELECT only"},
    {"name": "search_seo_observable_by_dtc", "volatility": "STABLE", "reason": "SELECT only"},
    {"name": "show_limit", "volatility": "STABLE", "reason": "SELECT only"},
    {"name": "table_exists", "volatility": "VOLATILE", "reason": "SELECT only"},
    {"name": "test_pieces_relation_access", "volatility": "VOLATILE", "reason": "SELECT only"},
    {"name": "validate_content_full", "volatility": "VOLATILE", "reason": "Validation only"},
    {"name": "validate_lexique_allumage", "volatility": "VOLATILE", "reason": "Validation only"},
    {"name": "validate_lexique_amortisseur", "volatility": "VOLATILE", "reason": "Validation only"},
    {"name": "validate_lexique_direction", "volatility": "VOLATILE", "reason": "Validation only"},
    {"name": "validate_lexique_embrayage", "volatility": "VOLATILE", "reason": "Validation only"},
    {"name": "validate_lexique_entrainement", "volatility": "VOLATILE", "reason": "Validation only"},
    {"name": "validate_lexique_freinage", "volatility": "VOLATILE", "reason": "Validation only"},
    {"name": "validate_lexique_support_moteur", "volatility": "VOLATILE", "reason": "Validation only"},
    {"name": "validate_seo_content", "volatility": "VOLATILE", "reason": "Validation only"},
    {"name": "validate_staging_brands", "volatility": "VOLATILE", "reason": "Validation only"},
    {"name": "get_homepage_data_optimized", "volatility": "VOLATILE", "reason": "Read-only optimization (migrated from P2)"},
    {"name": "get_brand_page_data_optimized", "volatility": "VOLATILE", "reason": "Read-only optimization (migrated from P2)"},
    {"name": "get_vehicle_page_data_optimized", "volatility": "VOLATILE", "reason": "Read-only optimization (migrated from P2)"},
    {"name": "get_gamme_page_data_optimized", "volatility": "VOLATILE", "reason": "Read-only optimization (migrated from P2)"},
    {"name": "get_brand_bestsellers_optimized", "volatility": "VOLATILE", "reason": "Read-only optimization (migrated from P2)"},
    {"name": "get_pieces_for_type_gamme", "volatility": "VOLATILE", "reason": "Read-only optimization (migrated from P2)"},
    {"name": "get_pieces_for_type_gamme_v3", "volatility": "VOLATILE", "reason": "Read-only optimization (migrated from P2)"},
    {"name": "get_oem_refs_for_vehicle", "volatility": "VOLATILE", "reason": "Read-only optimization (migrated from P2)"},
    {"name": "get_substitution_data", "volatility": "VOLATILE", "reason": "Read-only optimization (migrated from P2)"},
    {"name": "rm_get_listing_page", "volatility": "VOLATILE", "reason": "Read-only cache (migrated from P2)"},
    {"name": "rm_get_page_complete", "volatility": "VOLATILE", "reason": "Read-only cache (migrated from P2)"},
    {"name": "rm_get_page_complete_v2", "volatility": "VOLATILE", "reason": "Read-only cache (migrated from P2)"}
  ]
}
